ktblast/__init__.py
ktblast/ktblast.py
ktblast/unfold.py
utils/__init__.py
utils/kt2xf.py
utils/kt_undersample_2d.py
ktblast-0.1.0.dist-info/LICENSE
ktblast-0.1.0.dist-info/METADATA
ktblast-0.1.0.dist-info/WHEEL
ktblast-0.1.0.dist-info/top_level.txt
ktblast-0.1.0.dist-info/RECORD
