Metadata-Version: 2.1
Name: ktblast
Version: 0.1.0
Summary: Python implementation of the k-t BLAST algorithm.
Home-page: https://github.com/mckib2/ktblast
Author: Nicholas McKibben
Author-email: nicholas.bgp@gmail.com
License: GPLv3
Keywords: mri BLAST parallel-imaging image-reconstruction python
Platform: UNKNOWN
Requires-Python: >=3.5
Requires-Dist: numpy (>=1.16.4)
Requires-Dist: matplotlib (>=2.2.4)
Requires-Dist: phantominator (>=0.3.2)
Requires-Dist: scikit-image (>=0.15.0)
Requires-Dist: tqdm (>=4.32.2)
